odoo/addons/budget_control_revision/README.rst
odoo/addons/budget_control_revision/__init__.py
odoo/addons/budget_control_revision/__manifest__.py
odoo/addons/budget_control_revision/hooks.py
odoo/addons/budget_control_revision/data/budget_revision_data.xml
odoo/addons/budget_control_revision/models/__init__.py
odoo/addons/budget_control_revision/models/budget_control.py
odoo/addons/budget_control_revision/models/budget_period.py
odoo/addons/budget_control_revision/models/budget_plan.py
odoo/addons/budget_control_revision/models/res_company.py
odoo/addons/budget_control_revision/models/res_config_settings.py
odoo/addons/budget_control_revision/readme/CONTRIBUTORS.md
odoo/addons/budget_control_revision/readme/DESCRIPTION.md
odoo/addons/budget_control_revision/readme/USAGE.md
odoo/addons/budget_control_revision/report/__init__.py
odoo/addons/budget_control_revision/report/budget_monitor_report.py
odoo/addons/budget_control_revision/report/budget_monitor_report_view.xml
odoo/addons/budget_control_revision/report/budget_monitor_revision_report.py
odoo/addons/budget_control_revision/report/budget_monitor_revision_view.xml
odoo/addons/budget_control_revision/security/ir.model.access.csv
odoo/addons/budget_control_revision/static/description/icon.png
odoo/addons/budget_control_revision/static/description/index.html
odoo/addons/budget_control_revision/tests/__init__.py
odoo/addons/budget_control_revision/tests/test_budget_control_revision.py
odoo/addons/budget_control_revision/views/budget_control_view.xml
odoo/addons/budget_control_revision/views/budget_plan_view.xml
odoo/addons/budget_control_revision/views/res_config_settings_views.xml
odoo_addon_budget_control_revision-18.0.1.1.0.dist-info/METADATA
odoo_addon_budget_control_revision-18.0.1.1.0.dist-info/WHEEL
odoo_addon_budget_control_revision-18.0.1.1.0.dist-info/top_level.txt
odoo_addon_budget_control_revision-18.0.1.1.0.dist-info/RECORD
